aca/__init__.py
aca/aca.h
aca/aca_cpp.cpp
aca/aca_cpp.cpython-36m-darwin.so
aca/aca_cpp.pyx
aca/all.h
aca/automaton.cpp
aca/automaton.h
aca/example1.py
aca/example2.py
aca/example3.py
aca/example4.py
aca/example5.py
aca/match.cpp
aca/match.h
aca/node.cpp
aca/node.h
aca/test/__init__.py
aca/test/test_example_names.py
aca/test/test_get_matches.py
aca/test/test_has_pattern.py
aca/test/test_has_prefix.py
aca/test/test_iterations.py
aca/test/test_map_interface.py
aca/test/test_remove_overlaps.py
aca/test/test_serialize.py
aca/test/test_serialize_newlines.py
aca-1.0.dist-info/.DS_Store
aca-1.0.dist-info/DESCRIPTION.rst
aca-1.0.dist-info/METADATA
aca-1.0.dist-info/RECORD
aca-1.0.dist-info/WHEEL
aca-1.0.dist-info/metadata.json
aca-1.0.dist-info/top_level.txt
