Metadata-Version: 2.0
Name: aca
Version: 1.0
Summary: Aho-Corasick automaton implementation in C++
Home-page: https://github.com/tpetmanson/aca
Author: Timo Petmanson @Funderbeam
Author-email: tpetmanson@gmail.com
License: GPLv3
Platform: UNKNOWN
Classifier: Intended Audience :: Developers
Classifier: Topic :: Text Processing
Classifier: Topic :: Text Processing :: Linguistic
Classifier: Programming Language :: Python :: 3.4
Classifier: Programming Language :: Python :: 3.5
Classifier: Programming Language :: Python :: 3.6
Requires-Dist: Cython
Requires-Dist: wheel
Requires-Dist: six
Requires-Dist: pytest
